{
  "nodes": [
    {
      "id": "W1482603307"
    },
    {
      "id": "W1485415000"
    },
    {
      "id": "W1543603003"
    },
    {
      "id": "W1560892771"
    },
    {
      "id": "W1566965859"
    },
    {
      "id": "W1594506861"
    },
    {
      "id": "W1608703863"
    },
    {
      "id": "W1727604698"
    },
    {
      "id": "W177073152"
    },
    {
      "id": "W1965506462"
    },
    {
      "id": "W1969438288"
    },
    {
      "id": "W1988629159"
    },
    {
      "id": "W1991363040"
    },
    {
      "id": "W1994618479"
    },
    {
      "id": "W1996790570"
    },
    {
      "id": "W1997223161"
    },
    {
      "id": "W2000534534"
    },
    {
      "id": "W2001222609"
    },
    {
      "id": "W2002127424"
    },
    {
      "id": "W2005197983"
    },
    {
      "id": "W2006045909"
    },
    {
      "id": "W2012306983"
    },
    {
      "id": "W2018934406"
    },
    {
      "id": "W2019190770"
    },
    {
      "id": "W2019307057"
    },
    {
      "id": "W2025922793"
    },
    {
      "id": "W2029629075"
    },
    {
      "id": "W2034070517"
    },
    {
      "id": "W2036812736"
    },
    {
      "id": "W2041971124"
    },
    {
      "id": "W2043334098"
    },
    {
      "id": "W2045483011"
    },
    {
      "id": "W2055072931"
    },
    {
      "id": "W2057156398"
    },
    {
      "id": "W2060810539"
    },
    {
      "id": "W2063152519"
    },
    {
      "id": "W2066864051"
    },
    {
      "id": "W2071106779"
    },
    {
      "id": "W2077205830"
    },
    {
      "id": "W2078206416"
    },
    {
      "id": "W2078790577"
    },
    {
      "id": "W2083991128"
    },
    {
      "id": "W2084679526"
    },
    {
      "id": "W2086963342"
    },
    {
      "id": "W2089371205"
    },
    {
      "id": "W2097177823"
    },
    {
      "id": "W2098391435"
    },
    {
      "id": "W2105672294"
    },
    {
      "id": "W2107040678"
    },
    {
      "id": "W2119956801"
    },
    {
      "id": "W2120196032"
    },
    {
      "id": "W2123607122"
    },
    {
      "id": "W2125027853"
    },
    {
      "id": "W2127006916"
    },
    {
      "id": "W2141134789"
    },
    {
      "id": "W2163856568"
    },
    {
      "id": "W2168594645"
    },
    {
      "id": "W2169216879"
    },
    {
      "id": "W2203067890"
    },
    {
      "id": "W2462407094"
    },
    {
      "id": "W2510204365"
    },
    {
      "id": "W2555828157"
    },
    {
      "id": "W2575993503"
    },
    {
      "id": "W2755158994"
    },
    {
      "id": "W2759497469"
    },
    {
      "id": "W2810057462"
    },
    {
      "id": "W2891331903"
    },
    {
      "id": "W2893099989"
    },
    {
      "id": "W2912528171"
    },
    {
      "id": "W2925108882"
    },
    {
      "id": "W2942548857"
    },
    {
      "id": "W2943268109"
    },
    {
      "id": "W297216978"
    },
    {
      "id": "W3013047099"
    },
    {
      "id": "W3100097287"
    },
    {
      "id": "W3132766222"
    },
    {
      "id": "W3147643540"
    },
    {
      "id": "W3175082292"
    },
    {
      "id": "W3179761913"
    },
    {
      "id": "W3195988224"
    },
    {
      "id": "W3209826039"
    },
    {
      "id": "W4206010013"
    },
    {
      "id": "W4210886241"
    },
    {
      "id": "W4226255806"
    },
    {
      "id": "W4231394154"
    },
    {
      "id": "W4286611282"
    },
    {
      "id": "W4385261241"
    },
    {
      "id": "W4386408979"
    },
    {
      "id": "W4387998215"
    },
    {
      "id": "W4389074848"
    },
    {
      "id": "W4390481019"
    },
    {
      "id": "W4391811388"
    },
    {
      "id": "W4392133461"
    },
    {
      "id": "W4402514985"
    },
    {
      "id": "W4409325815"
    },
    {
      "id": "W4411406658"
    },
    {
      "id": "W4414929696"
    },
    {
      "id": "W4415760605"
    },
    {
      "id": "W65668535"
    }
  ],
  "edges": [
    {
      "source": "W1543603003",
      "target": "W2169216879"
    },
    {
      "source": "W1988629159",
      "target": "W2169216879"
    },
    {
      "source": "W1991363040",
      "target": "W2169216879"
    },
    {
      "source": "W2025922793",
      "target": "W2169216879"
    },
    {
      "source": "W2041971124",
      "target": "W2169216879"
    },
    {
      "source": "W2045483011",
      "target": "W2169216879"
    },
    {
      "source": "W2086963342",
      "target": "W2169216879"
    },
    {
      "source": "W2098391435",
      "target": "W2169216879"
    },
    {
      "source": "W2141134789",
      "target": "W2169216879"
    },
    {
      "source": "W2163856568",
      "target": "W2169216879"
    },
    {
      "source": "W2168594645",
      "target": "W2169216879"
    },
    {
      "source": "W2169216879",
      "target": "W1482603307"
    },
    {
      "source": "W2169216879",
      "target": "W1485415000"
    },
    {
      "source": "W2169216879",
      "target": "W1560892771"
    },
    {
      "source": "W2169216879",
      "target": "W1566965859"
    },
    {
      "source": "W2169216879",
      "target": "W1594506861"
    },
    {
      "source": "W2169216879",
      "target": "W1608703863"
    },
    {
      "source": "W2169216879",
      "target": "W1727604698"
    },
    {
      "source": "W2169216879",
      "target": "W177073152"
    },
    {
      "source": "W2169216879",
      "target": "W1965506462"
    },
    {
      "source": "W2169216879",
      "target": "W1969438288"
    },
    {
      "source": "W2169216879",
      "target": "W1994618479"
    },
    {
      "source": "W2169216879",
      "target": "W1996790570"
    },
    {
      "source": "W2169216879",
      "target": "W1997223161"
    },
    {
      "source": "W2169216879",
      "target": "W2000534534"
    },
    {
      "source": "W2169216879",
      "target": "W2001222609"
    },
    {
      "source": "W2169216879",
      "target": "W2002127424"
    },
    {
      "source": "W2169216879",
      "target": "W2005197983"
    },
    {
      "source": "W2169216879",
      "target": "W2006045909"
    },
    {
      "source": "W2169216879",
      "target": "W2012306983"
    },
    {
      "source": "W2169216879",
      "target": "W2018934406"
    },
    {
      "source": "W2169216879",
      "target": "W2019190770"
    },
    {
      "source": "W2169216879",
      "target": "W2019307057"
    },
    {
      "source": "W2169216879",
      "target": "W2029629075"
    },
    {
      "source": "W2169216879",
      "target": "W2034070517"
    },
    {
      "source": "W2169216879",
      "target": "W2036812736"
    },
    {
      "source": "W2169216879",
      "target": "W2043334098"
    },
    {
      "source": "W2169216879",
      "target": "W2045483011"
    },
    {
      "source": "W2169216879",
      "target": "W2055072931"
    },
    {
      "source": "W2169216879",
      "target": "W2057156398"
    },
    {
      "source": "W2169216879",
      "target": "W2060810539"
    },
    {
      "source": "W2169216879",
      "target": "W2063152519"
    },
    {
      "source": "W2169216879",
      "target": "W2066864051"
    },
    {
      "source": "W2169216879",
      "target": "W2071106779"
    },
    {
      "source": "W2169216879",
      "target": "W2077205830"
    },
    {
      "source": "W2169216879",
      "target": "W2078206416"
    },
    {
      "source": "W2169216879",
      "target": "W2078790577"
    },
    {
      "source": "W2169216879",
      "target": "W2083991128"
    },
    {
      "source": "W2169216879",
      "target": "W2084679526"
    },
    {
      "source": "W2169216879",
      "target": "W2086963342"
    },
    {
      "source": "W2169216879",
      "target": "W2089371205"
    },
    {
      "source": "W2169216879",
      "target": "W2097177823"
    },
    {
      "source": "W2169216879",
      "target": "W2105672294"
    },
    {
      "source": "W2169216879",
      "target": "W2107040678"
    },
    {
      "source": "W2169216879",
      "target": "W2119956801"
    },
    {
      "source": "W2169216879",
      "target": "W2120196032"
    },
    {
      "source": "W2169216879",
      "target": "W2123607122"
    },
    {
      "source": "W2169216879",
      "target": "W2125027853"
    },
    {
      "source": "W2169216879",
      "target": "W2127006916"
    },
    {
      "source": "W2169216879",
      "target": "W297216978"
    },
    {
      "source": "W2169216879",
      "target": "W65668535"
    },
    {
      "source": "W2203067890",
      "target": "W2169216879"
    },
    {
      "source": "W2462407094",
      "target": "W2169216879"
    },
    {
      "source": "W2510204365",
      "target": "W2169216879"
    },
    {
      "source": "W2555828157",
      "target": "W2169216879"
    },
    {
      "source": "W2575993503",
      "target": "W2169216879"
    },
    {
      "source": "W2755158994",
      "target": "W2169216879"
    },
    {
      "source": "W2759497469",
      "target": "W2169216879"
    },
    {
      "source": "W2810057462",
      "target": "W2169216879"
    },
    {
      "source": "W2891331903",
      "target": "W2169216879"
    },
    {
      "source": "W2893099989",
      "target": "W2169216879"
    },
    {
      "source": "W2912528171",
      "target": "W2169216879"
    },
    {
      "source": "W2925108882",
      "target": "W2169216879"
    },
    {
      "source": "W2942548857",
      "target": "W2169216879"
    },
    {
      "source": "W2943268109",
      "target": "W2169216879"
    },
    {
      "source": "W3013047099",
      "target": "W2169216879"
    },
    {
      "source": "W3100097287",
      "target": "W2169216879"
    },
    {
      "source": "W3132766222",
      "target": "W2169216879"
    },
    {
      "source": "W3147643540",
      "target": "W2169216879"
    },
    {
      "source": "W3175082292",
      "target": "W2169216879"
    },
    {
      "source": "W3179761913",
      "target": "W2169216879"
    },
    {
      "source": "W3195988224",
      "target": "W2169216879"
    },
    {
      "source": "W3209826039",
      "target": "W2169216879"
    },
    {
      "source": "W4206010013",
      "target": "W2169216879"
    },
    {
      "source": "W4210886241",
      "target": "W2169216879"
    },
    {
      "source": "W4226255806",
      "target": "W2169216879"
    },
    {
      "source": "W4231394154",
      "target": "W2169216879"
    },
    {
      "source": "W4286611282",
      "target": "W2169216879"
    },
    {
      "source": "W4385261241",
      "target": "W2169216879"
    },
    {
      "source": "W4386408979",
      "target": "W2169216879"
    },
    {
      "source": "W4387998215",
      "target": "W2169216879"
    },
    {
      "source": "W4389074848",
      "target": "W2169216879"
    },
    {
      "source": "W4390481019",
      "target": "W2169216879"
    },
    {
      "source": "W4391811388",
      "target": "W2169216879"
    },
    {
      "source": "W4392133461",
      "target": "W2169216879"
    },
    {
      "source": "W4402514985",
      "target": "W2169216879"
    },
    {
      "source": "W4409325815",
      "target": "W2169216879"
    },
    {
      "source": "W4411406658",
      "target": "W2169216879"
    },
    {
      "source": "W4414929696",
      "target": "W2169216879"
    },
    {
      "source": "W4415760605",
      "target": "W2169216879"
    }
  ]
}
