{
  "packageName": "com.trebuchetdynamics.fractal.forge",
  "source": "Generated from live Play listing locales on 2026-07-02. Update with scripts/update-play-store-listings.sh.",
  "count": "974 production fractals",
  "locales": {
    "en-US": {
      "title": "Fractal Forge: Fractal Art",
      "shortDescription": "974 GPU fractal art & wallpapers. Mandelbrot, Julia, deep zoom. No ads.",
      "fullDescription": "Fractal Forge is a fast, private fractal explorer for creating generative math art, fractal wallpapers, and visual studies. Explore 974 production fractals with GPU-accelerated GLSL shaders where supported, deep zoom, and real-time controls.\n\nDiscover classic and modern fractal families:\n• Mandelbrot and Julia sets, Burning Ship, Tricorn, Celtic, Buffalo, Nova, Phoenix, and Lyapunov maps\n• Newton, Halley, Householder, Schroeder, and other root-finding basins\n• Strange attractors, cellular automata, space-filling curves, tilings, and IFS systems\n• 3D ray-marched worlds such as Mandelbulb, Mandelbox, and quaternion-style fractals\n\nUse curated presets to jump to rich regions, adjust iterations, palettes, color styles, orbit traps, distance estimation, normal-map relief, and visual parameters, then export high-resolution PNG images for wallpaper, sharing, teaching, or study.\n\nFeatures:\n• 974 production fractal modules\n• GPU-powered rendering where supported\n• Deep zoom and pan controls\n• 60+ color schemes with smooth coloring\n• Dual Mandelbrot / Julia viewer\n• Auto-explore mode for discovering interesting regions\n• Randomizer for instant new looks\n• Looper for animated parameter motion\n• Fractal Music generation from visual scans\n• Wallpaper apply/save tools\n• Camera overlay experiments that stay on device\n• Export and share tools\n• Accessibility support with high contrast, reduced motion, labels, and configurable touch targets\n\nPrivate by design: no ads, no tracking, no account required, and no data collection.\n\nUse Fractal Forge to create fractal art, study nonlinear systems, teach math patterns, make unique wallpapers, or relax with infinite visual worlds."
    },
    "es-ES": {
      "title": "Fractal Forge",
      "shortDescription": "974 fractales GPU, fondos, música, looper, aleatorio, sin anuncios.",
      "fullDescription": "Fractal Forge es un explorador de fractales rápido y privado para artistas, estudiantes, docentes y cualquier persona curiosa por los patrones matemáticos.\n\nExplora 974 fractales de producción en familias clásicas y modernas:\n• Mandelbrot, Julia, Burning Ship, Tricorn, Celtic, Buffalo, Nova, Phoenix y mapas de Lyapunov\n• Newton, Halley, Householder, Schroeder y otras cuencas de búsqueda de raíces\n• Atractores extraños, autómatas celulares, curvas de llenado de espacio, teselaciones y sistemas IFS\n• Mundos 3D por ray marching como Mandelbulb, Mandelbox y fractales de estilo cuaterniónico\n\nFractal Forge renderiza con shaders GLSL acelerados por GPU cuando el dispositivo lo permite, con rutas de precisión alternativas para exploración profunda. Usa presets seleccionados para saltar a regiones interesantes, ajusta iteraciones, paletas, estilos de color y parámetros visuales, y exporta imágenes PNG de alta resolución para fondos, compartir o estudiar.\n\nFunciones:\n• 974 módulos fractales de producción\n• Controles de zoom profundo y desplazamiento\n• Más de 60 esquemas de color con coloración suave, trampas orbitales, estimación de distancia, relieve normal-map y más\n• Visor doble Mandelbrot / Julia\n• Modo auto-explorar para descubrir regiones interesantes\n• Aleatorizador para crear nuevos aspectos al instante\n• Looper para animar parámetros\n• Generación de Fractal Music desde escaneos visuales\n• Herramientas para aplicar o guardar fondos de pantalla\n• Experimentos con cámara que permanecen en el dispositivo\n• Herramientas de exportación y compartir\n• Accesibilidad con alto contraste, movimiento reducido, etiquetas y objetivos táctiles configurables\n\nPrivado por diseño: sin anuncios, sin seguimiento, sin cuenta obligatoria y sin recopilación de datos."
    },
    "fr-FR": {
      "title": "Fractal Forge",
      "shortDescription": "974 fractales GPU, fonds d’écran, musique, looper, hasard, sans pub.",
      "fullDescription": "Fractal Forge est un explorateur de fractales rapide et privé pour les artistes, les élèves, les enseignants et toutes les personnes curieuses des motifs mathématiques.\n\nExplorez 974 fractales de production dans des familles classiques et modernes :\n• Mandelbrot, Julia, Burning Ship, Tricorn, Celtic, Buffalo, Nova, Phoenix et cartes de Lyapunov\n• Newton, Halley, Householder, Schroeder et autres bassins de recherche de racines\n• Attracteurs étranges, automates cellulaires, courbes remplissant l'espace, pavages et systèmes IFS\n• Mondes 3D en ray marching comme Mandelbulb, Mandelbox et fractales de type quaternion\n\nFractal Forge utilise des shaders GLSL accélérés par le GPU quand ils sont disponibles, avec des chemins de précision de secours pour l'exploration en zoom profond. Utilisez des préréglages soignés, ajustez les itérations, palettes, styles de couleur et paramètres visuels, puis exportez des images PNG haute résolution pour fond d'écran, partage ou étude.\n\nFonctions :\n• 974 modules fractals de production\n• Zoom profond et déplacement\n• Plus de 60 palettes avec coloration lisse, pièges orbitaux, estimation de distance, relief normal-map et plus\n• Double vue Mandelbrot / Julia\n• Mode auto-exploration\n• Aléatoire pour créer instantanément de nouveaux rendus\n• Looper pour animer les paramètres\n• Génération Fractal Music à partir de scans visuels\n• Outils pour appliquer ou enregistrer des fonds d’écran\n• Expériences avec caméra, traitées sur l'appareil\n• Exportation et partage\n• Accessibilité : contraste élevé, mouvement réduit, libellés et cibles tactiles configurables\n\nPrivé par conception : sans publicité, sans pistage, sans compte obligatoire et sans collecte de données."
    },
    "de-DE": {
      "title": "Fractal Forge",
      "shortDescription": "974 GPU-Fraktale, Wallpaper, Musik, Looper, Zufall, keine Werbung.",
      "fullDescription": "Fractal Forge ist ein schneller, privater Fraktal-Explorer für Künstler, Lernende, Lehrkräfte und alle, die mathematische Muster entdecken möchten.\n\nErkunde 974 Produktionsfraktale aus klassischen und modernen Familien:\n• Mandelbrot, Julia, Burning Ship, Tricorn, Celtic, Buffalo, Nova, Phoenix und Lyapunov-Karten\n• Newton, Halley, Householder, Schroeder und weitere Wurzelfindungs-Basins\n• Seltsame Attraktoren, zelluläre Automaten, raumfüllende Kurven, Kachelungen und IFS-Systeme\n• 3D-Raymarching-Welten wie Mandelbulb, Mandelbox und quaternionartige Fraktale\n\nFractal Forge rendert, wenn möglich, mit GPU-beschleunigten GLSL-Shadern und nutzt Präzisions-Fallbacks für tiefere Erkundung. Springe mit kuratierten Presets zu spannenden Regionen, ändere Iterationen, Paletten, Farbstile und visuelle Parameter und exportiere hochauflösende PNG-Bilder für Wallpaper, Teilen oder Unterricht.\n\nFunktionen:\n• 974 Produktions-Fraktalmodule\n• Tiefzoom und Verschieben\n• Über 60 Farbschemata mit Smooth Coloring, Orbit Traps, Distance Estimation, Normal-Map-Relief und mehr\n• Dualer Mandelbrot-/Julia-Viewer\n• Auto-Explore-Modus\n• Zufallsgenerator für sofort neue Looks\n• Looper für animierte Parameterbewegung\n• Fractal-Music-Erzeugung aus visuellen Scans\n• Wallpaper anwenden oder speichern\n• Kamera-Overlay-Experimente, die auf dem Gerät bleiben\n• Export- und Teilen-Werkzeuge\n• Barrierefreiheit mit hohem Kontrast, reduzierter Bewegung, Labels und konfigurierbaren Touch-Zielen\n\nPrivat by Design: keine Werbung, kein Tracking, kein Konto erforderlich und keine Datenerfassung."
    },
    "pt-BR": {
      "title": "Fractal Forge",
      "shortDescription": "974 fractais GPU, wallpapers, música, looper, aleatório, sem anúncios.",
      "fullDescription": "Fractal Forge é um explorador de fractais rápido e privado para artistas, estudantes, professores e qualquer pessoa curiosa sobre padrões matemáticos.\n\nExplore 974 fractais de produção em famílias clássicas e modernas:\n• Mandelbrot, Julia, Burning Ship, Tricorn, Celtic, Buffalo, Nova, Phoenix e mapas de Lyapunov\n• Newton, Halley, Householder, Schroeder e outras bacias de busca de raízes\n• Atratores estranhos, autômatos celulares, curvas de preenchimento de espaço, ladrilhamentos e sistemas IFS\n• Mundos 3D por ray marching, como Mandelbulb, Mandelbox e fractais de estilo quaterniônico\n\nFractal Forge renderiza com shaders GLSL acelerados por GPU quando disponíveis, com caminhos de precisão alternativos para exploração em zoom profundo. Use presets selecionados, ajuste iterações, paletas, estilos de cor e parâmetros visuais, e exporte imagens PNG em alta resolução para papéis de parede, compartilhamento ou estudo.\n\nRecursos:\n• 974 módulos fractais de produção\n• Zoom profundo e panorâmica\n• Mais de 60 esquemas de cores com coloração suave, armadilhas orbitais, estimativa de distância, relevo normal-map e mais\n• Visualizador duplo Mandelbrot / Julia\n• Modo auto-explorar\n• Aleatorizador para criar novos visuais instantaneamente\n• Looper para animar parâmetros\n• Geração de Fractal Music a partir de varreduras visuais\n• Ferramentas para aplicar ou salvar wallpapers\n• Experimentos com câmera que ficam no dispositivo\n• Ferramentas de exportação e compartilhamento\n• Acessibilidade com alto contraste, movimento reduzido, rótulos e alvos de toque configuráveis\n\nPrivado por design: sem anúncios, sem rastreamento, sem conta obrigatória e sem coleta de dados."
    },
    "ja-JP": {
      "title": "Fractal Forge",
      "shortDescription": "974種類のGPUフラクタル。壁紙、音楽、ルーパー、ランダム、広告なし。",
      "fullDescription": "Fractal Forge は、数学的な模様をすばやく安全に探索できるフラクタルビューアです。アート制作、学習、教育、リラックスした鑑賞に向いています。\n\n974種類の本番フラクタルを収録:\n• Mandelbrot、Julia、Burning Ship、Tricorn、Celtic、Buffalo、Nova、Phoenix、Lyapunov\n• Newton、Halley、Householder、Schroeder などの根探索フラクタル\n• ストレンジアトラクタ、セルオートマトン、空間充填曲線、タイリング、IFS\n• Mandelbulb、Mandelbox、クォータニオン風の3Dレイマーチング世界\n\n対応環境ではGPUのGLSLシェーダで高速描画します。深いズームでは精度を保つためのフォールバック経路も用意しています。プリセットで美しい領域へ移動し、反復回数、パレット、色付け、表示パラメータを調整できます。高解像度PNGとして保存し、壁紙、共有、学習資料に使えます。\n\n主な機能:\n• 974種類の本番フラクタルモジュール\n• 深いズームとパン操作\n• 60以上の配色、スムーズカラー、軌道トラップ、距離推定、法線マップ風レリーフなど\n• Mandelbrot / Julia のデュアル表示\n• 興味深い領域を探す自動探索モード\n• ランダマイザーで新しい見た目をすばやく生成\n• パラメータを動かすルーパー\n• ビジュアルスキャンからの Fractal Music 生成\n• 壁紙として適用または保存\n• 端末内で処理されるカメラオーバーレイ実験\n• エクスポートと共有\n• 高コントラスト、動きの低減、ラベル、タッチ目標設定などのアクセシビリティ\n\n広告なし。トラッキングなし。アカウント不要。データ収集なし。"
    },
    "ko-KR": {
      "title": "Fractal Forge",
      "shortDescription": "974개 GPU 프랙털: 배경화면, 음악, 루퍼, 랜덤, 광고 없음.",
      "fullDescription": "Fractal Forge는 수학적 패턴을 빠르고 개인적으로 탐색하는 프랙털 앱입니다. 아티스트, 학습자, 교사, 그리고 생성 예술을 좋아하는 모든 사람에게 적합합니다.\n\n974개의 프로덕션 프랙털을 탐색하세요:\n• Mandelbrot, Julia, Burning Ship, Tricorn, Celtic, Buffalo, Nova, Phoenix, Lyapunov 맵\n• Newton, Halley, Householder, Schroeder 등 근 찾기 basin\n• 이상한 끌개, 셀룰러 오토마타, 공간 채움 곡선, 타일링, IFS 시스템\n• Mandelbulb, Mandelbox, 쿼터니언 스타일 3D 레이마칭 프랙털\n\n지원되는 기기에서는 GPU 기반 GLSL 셰이더로 부드럽게 렌더링합니다. 더 깊은 확대를 위해 정밀도 보조 경로도 제공합니다. 큐레이션된 프리셋으로 멋진 영역을 바로 열고, 반복 횟수, 팔레트, 색상 스타일, 시각 파라미터를 조정한 뒤 고해상도 PNG로 저장하거나 공유할 수 있습니다.\n\n기능:\n• 974개 프로덕션 프랙털 모듈\n• 딥줌과 팬 조작\n• 60개 이상의 색상 구성, 부드러운 컬러링, 궤도 트랩, 거리 추정, 노멀맵 릴리프 등\n• Mandelbrot / Julia 듀얼 뷰어\n• 흥미로운 영역을 찾는 자동 탐색 모드\n• 랜덤 기능으로 즉시 새로운 모습 생성\n• 파라미터 움직임을 위한 루퍼\n• 시각 스캔 기반 Fractal Music 생성\n• 배경화면 적용 및 저장 도구\n• 기기 안에서 처리되는 카메라 오버레이 실험\n• 내보내기 및 공유 도구\n• 고대비, 줄어든 동작, 스크린 리더 라벨, 조절 가능한 터치 대상\n\n개인정보 중심 설계: 광고 없음, 추적 없음, 계정 필요 없음, 데이터 수집 없음."
    },
    "it-IT": {
      "title": "Fractal Forge",
      "shortDescription": "974 frattali GPU, sfondi, musica, looper, randomizer, senza ads.",
      "fullDescription": "Fractal Forge è un esploratore di frattali veloce e privato per artisti, studenti, docenti e chiunque ami i pattern matematici.\n\nEsplora 974 frattali di produzione tra famiglie classiche e moderne:\n• Mandelbrot, Julia, Burning Ship, Tricorn, Celtic, Buffalo, Nova, Phoenix e mappe di Lyapunov\n• Newton, Halley, Householder, Schroeder e altri bacini di ricerca delle radici\n• Attrattori strani, automi cellulari, curve riempitive, tassellazioni e sistemi IFS\n• Mondi 3D in ray marching come Mandelbulb, Mandelbox e frattali in stile quaternione\n\nFractal Forge usa shader GLSL accelerati dalla GPU dove supportati, con percorsi di precisione alternativi per esplorazioni più profonde. Usa preset curati, regola iterazioni, palette, stili colore e parametri visivi, poi esporta PNG ad alta risoluzione per sfondi, condivisione o studio.\n\nFunzioni:\n• 974 moduli frattali di produzione\n• Zoom profondo e panoramica\n• Oltre 60 schemi colore con colorazione liscia, orbit trap, stima della distanza, rilievo normal-map e altro\n• Vista doppia Mandelbrot / Julia\n• Modalità auto-esplora\n• Randomizer per creare nuovi look all’istante\n• Looper per animare i parametri\n• Generazione Fractal Music da scansioni visive\n• Strumenti per applicare o salvare sfondi\n• Esperimenti con overlay fotocamera elaborati sul dispositivo\n• Esportazione e condivisione\n• Accessibilità con alto contrasto, movimento ridotto, etichette e target touch configurabili\n\nPrivato per scelta: niente pubblicità, niente tracciamento, nessun account richiesto e nessuna raccolta dati."
    },
    "nl-NL": {
      "title": "Fractal Forge",
      "shortDescription": "974 GPU-fractals, wallpapers, muziek, looper, randomizer, geen ads.",
      "fullDescription": "Fractal Forge is een snelle, private fractalverkenner voor kunstenaars, leerlingen, docenten en iedereen die nieuwsgierig is naar wiskundige patronen.\n\nVerken 974 productiefractals uit klassieke en moderne families:\n• Mandelbrot, Julia, Burning Ship, Tricorn, Celtic, Buffalo, Nova, Phoenix en Lyapunov-kaarten\n• Newton, Halley, Householder, Schroeder en andere wortelzoekende basins\n• Strange attractors, cellulaire automaten, ruimtevullende krommen, betegelingen en IFS-systemen\n• 3D-raymarchingwerelden zoals Mandelbulb, Mandelbox en quaternion-achtige fractals\n\nFractal Forge rendert waar mogelijk met GPU-versnelde GLSL-shaders en gebruikt precisie-fallbacks voor diepere verkenning. Gebruik zorgvuldig gekozen presets, pas iteraties, paletten, kleurstijlen en visuele parameters aan, en exporteer PNG-afbeeldingen in hoge resolutie voor wallpapers, delen of studie.\n\nFuncties:\n• 974 productie-fractalmodules\n• Diep zoomen en pannen\n• Meer dan 60 kleurenschema's met vloeiende kleuring, orbit traps, afstandsschatting, normal-map relief en meer\n• Dubbele Mandelbrot / Julia-viewer\n• Auto-verkennen voor interessante gebieden\n• Randomizer voor direct nieuwe looks\n• Looper voor geanimeerde parameterbeweging\n• Fractal Music-generatie uit visuele scans\n• Wallpaper toepassen of opslaan\n• Camera-overlay-experimenten die op het apparaat blijven\n• Exporteren en delen\n• Toegankelijkheid met hoog contrast, minder beweging, labels en instelbare aanraakdoelen\n\nPrivacy by design: geen advertenties, geen tracking, geen account vereist en geen gegevensverzameling."
    },
    "pl-PL": {
      "title": "Fractal Forge",
      "shortDescription": "974 fraktale GPU, tapety, muzyka, looper, losowanie, bez reklam.",
      "fullDescription": "Fractal Forge to szybka i prywatna przeglądarka fraktali dla artystów, uczniów, nauczycieli i wszystkich ciekawych matematycznych wzorów.\n\nOdkrywaj 974 produkcyjne fraktale z klasycznych i nowoczesnych rodzin:\n• Mandelbrot, Julia, Burning Ship, Tricorn, Celtic, Buffalo, Nova, Phoenix i mapy Lyapunova\n• Newton, Halley, Householder, Schroeder i inne baseny metod znajdowania pierwiastków\n• Dziwne atraktory, automaty komórkowe, krzywe wypełniające przestrzeń, parkietaż i systemy IFS\n• Światy 3D ray marching, takie jak Mandelbulb, Mandelbox i fraktale w stylu kwaternionów\n\nFractal Forge renderuje za pomocą shaderów GLSL przyspieszanych przez GPU tam, gdzie jest to obsługiwane, z alternatywnymi ścieżkami precyzji dla głębszej eksploracji. Używaj przygotowanych presetów, zmieniaj iteracje, palety, style kolorów i parametry wizualne, a następnie eksportuj obrazy PNG w wysokiej rozdzielczości.\n\nFunkcje:\n• 974 produkcyjne moduły fraktali\n• Głęboki zoom i przesuwanie\n• Ponad 60 schematów kolorów: płynne kolorowanie, orbit traps, estymacja odległości, relief normal-map i więcej\n• Podwójny widok Mandelbrot / Julia\n• Tryb automatycznego odkrywania\n• Randomizer do natychmiastowych nowych wyglądów\n• Looper do animowania parametrów\n• Generowanie Fractal Music ze skanów wizualnych\n• Narzędzia do ustawiania i zapisywania tapet\n• Eksperymenty z nakładką kamery pozostające na urządzeniu\n• Eksport i udostępnianie\n• Dostępność: wysoki kontrast, ograniczony ruch, etykiety i konfigurowalne cele dotykowe\n\nPrywatność z założenia: bez reklam, bez śledzenia, bez konta i bez zbierania danych."
    },
    "sv-SE": {
      "title": "Fractal Forge",
      "shortDescription": "974 GPU-fraktaler, bakgrunder, musik, looper, slump, inga annonser.",
      "fullDescription": "Fractal Forge är en snabb och privat fraktalutforskare för konstnärer, elever, lärare och alla som är nyfikna på matematiska mönster.\n\nUtforska 974 produktionsfraktaler i klassiska och moderna familjer:\n• Mandelbrot, Julia, Burning Ship, Tricorn, Celtic, Buffalo, Nova, Phoenix och Lyapunov-kartor\n• Newton, Halley, Householder, Schroeder och andra rotfinningsbassänger\n• Strange attractors, cellulära automater, rymdfyllande kurvor, tesselleringar och IFS-system\n• 3D-raymarchade världar som Mandelbulb, Mandelbox och quaternion-liknande fraktaler\n\nFractal Forge renderar med GPU-accelererade GLSL-shaders där det stöds, med precisionsvägar för djupare utforskning. Använd utvalda presets, justera iterationer, paletter, färgstilar och visuella parametrar, och exportera högupplösta PNG-bilder för bakgrunder, delning eller studier.\n\nFunktioner:\n• 974 produktionsfraktalmoduler\n• Djup zoom och panorering\n• Över 60 färgscheman med mjuk färgning, orbit traps, avståndsestimering, normal-map-relief och mer\n• Dubbel Mandelbrot / Julia-visare\n• Auto-utforska-läge\n• Slumpgenerator för nya uttryck direkt\n• Looper för animerad parameterrörelse\n• Fractal Music-generering från visuella skanningar\n• Verktyg för att använda eller spara bakgrunder\n• Kameraoverlay-experiment som stannar på enheten\n• Export och delning\n• Tillgänglighet med hög kontrast, minskad rörelse, etiketter och justerbara pekmål\n\nPrivat från början: inga annonser, ingen spårning, inget konto krävs och ingen datainsamling."
    },
    "zh-CN": {
      "title": "Fractal Forge",
      "shortDescription": "974 个 GPU 分形：壁纸、音乐、循环器、随机器、无广告。",
      "fullDescription": "Fractal Forge 是一款快速、注重隐私的分形探索器，适合艺术创作、学习、教学，以及所有喜欢数学图案的人。\n\n探索 974 个正式分形模块，覆盖经典与现代类型：\n• Mandelbrot、Julia、Burning Ship、Tricorn、Celtic、Buffalo、Nova、Phoenix、Lyapunov 映射\n• Newton、Halley、Householder、Schroeder 等求根盆地\n• 奇异吸引子、元胞自动机、空间填充曲线、平铺和 IFS 系统\n• Mandelbulb、Mandelbox、四元数风格等 3D 光线步进分形\n\n在支持的设备上，Fractal Forge 使用 GPU 加速的 GLSL 着色器进行实时渲染，并为更深层的探索提供精度回退路径。你可以使用精选预设进入精彩区域，调整迭代次数、调色板、着色方式和视觉参数，并导出高分辨率 PNG 图片用于壁纸、分享或学习。\n\n功能：\n• 974 个正式分形模块\n• 深度缩放与平移\n• 60 多种配色，支持平滑着色、轨道陷阱、距离估计、法线贴图浮雕等\n• Mandelbrot / Julia 双视图\n• 自动探索模式\n• 随机器可快速生成新效果\n• 循环器可动画化参数变化\n• 从视觉扫描生成 Fractal Music\n• 壁纸应用与保存工具\n• 保留在设备本地的相机叠加实验\n• 导出与分享工具\n• 高对比度、减少动态效果、屏幕阅读器标签和可配置触控目标\n\n隐私优先：无广告、无跟踪、无需账号、不收集数据。"
    },
    "zh-TW": {
      "title": "Fractal Forge",
      "shortDescription": "974 個 GPU 分形：桌布、音樂、循環器、隨機器、無廣告。",
      "fullDescription": "Fractal Forge 是一款快速、重視隱私的分形探索器，適合藝術創作、學習、教學，以及所有喜歡數學圖樣的人。\n\n探索 974 個正式分形模組，涵蓋經典與現代類型：\n• Mandelbrot、Julia、Burning Ship、Tricorn、Celtic、Buffalo、Nova、Phoenix、Lyapunov 映射\n• Newton、Halley、Householder、Schroeder 等求根盆地\n• 奇異吸引子、細胞自動機、空間填充曲線、平鋪與 IFS 系統\n• Mandelbulb、Mandelbox、四元數風格等 3D 光線步進分形\n\n在支援的裝置上，Fractal Forge 使用 GPU 加速的 GLSL 著色器即時渲染，並為更深層的探索提供精度備援路徑。你可以使用精選預設進入精彩區域，調整迭代次數、調色盤、著色方式與視覺參數，並匯出高解析度 PNG 圖片作為桌布、分享或學習使用。\n\n功能：\n• 974 個正式分形模組\n• 深度縮放與平移\n• 60 多種配色，支援平滑著色、軌道陷阱、距離估計、法線貼圖浮雕等\n• Mandelbrot / Julia 雙視圖\n• 自動探索模式\n• 隨機器可快速產生新效果\n• 循環器可動畫化參數變化\n• 從視覺掃描生成 Fractal Music\n• 桌布套用與儲存工具\n• 保留在裝置本機的相機疊加實驗\n• 匯出與分享工具\n• 高對比、減少動態效果、螢幕閱讀器標籤和可設定觸控目標\n\n隱私優先：無廣告、無追蹤、無需帳號、不收集資料。"
    },
    "hi-IN": {
      "title": "Fractal Forge",
      "shortDescription": "974 GPU फ्रैक्टल: wallpaper, music, looper, randomizer, no ads.",
      "fullDescription": "Fractal Forge कलाकारों, विद्यार्थियों, शिक्षकों और गणितीय पैटर्न में रुचि रखने वाले सभी लोगों के लिए तेज़ और निजी फ्रैक्टल एक्सप्लोरर है।\n\n974 प्रोडक्शन फ्रैक्टल खोजें, जिनमें क्लासिक और आधुनिक परिवार शामिल हैं:\n• Mandelbrot, Julia, Burning Ship, Tricorn, Celtic, Buffalo, Nova, Phoenix और Lyapunov मैप\n• Newton, Halley, Householder, Schroeder और अन्य root-finding basins\n• strange attractors, cellular automata, space-filling curves, tilings और IFS systems\n• Mandelbulb, Mandelbox और quaternion-style 3D ray-marched fractals\n\nसमर्थित डिवाइसों पर Fractal Forge GPU-powered GLSL shaders से smooth rendering करता है, और deep exploration के लिए precision fallback paths भी देता है। curated presets से खूबसूरत regions खोलें, iterations, palettes, color styles और visual parameters बदलें, फिर high-resolution PNG images wallpaper, sharing या study के लिए export करें।\n\nFeatures:\n• 974 production fractal modules\n• Deep zoom और pan controls\n• 60+ color schemes with smooth coloring, orbit traps, distance estimation, normal-map relief और more\n• Dual Mandelbrot / Julia viewer\n• interesting regions खोजने के लिए auto-explore mode\n• Randomizer से तुरंत नए looks\n• Parameter motion के लिए looper\n• Visual scans से Fractal Music generation\n• Wallpaper apply और save tools\n• device पर रहने वाले camera overlay experiments\n• Export और share tools\n• Accessibility: high contrast, reduced motion, labels और configurable touch targets\n\nPrivacy by design: no ads, no tracking, no account required, no data collection."
    },
    "id": {
      "title": "Fractal Forge",
      "shortDescription": "974 fraktal GPU, wallpaper, musik, looper, randomizer, tanpa iklan.",
      "fullDescription": "Fractal Forge adalah penjelajah fraktal yang cepat dan privat untuk seniman, pelajar, pendidik, dan siapa pun yang tertarik pada pola matematika.\n\nJelajahi 974 fraktal produksi dari keluarga klasik dan modern:\n• Mandelbrot, Julia, Burning Ship, Tricorn, Celtic, Buffalo, Nova, Phoenix, dan peta Lyapunov\n• Newton, Halley, Householder, Schroeder, dan basin pencarian akar lainnya\n• Strange attractors, cellular automata, kurva pengisi ruang, tiling, dan sistem IFS\n• Dunia 3D ray-marched seperti Mandelbulb, Mandelbox, dan fraktal bergaya quaternion\n\nFractal Forge merender dengan shader GLSL yang dipercepat GPU jika didukung, dengan jalur presisi cadangan untuk eksplorasi lebih dalam. Gunakan preset pilihan untuk membuka wilayah menarik, atur iterasi, palet, gaya warna, dan parameter visual, lalu ekspor gambar PNG resolusi tinggi untuk wallpaper, berbagi, atau belajar.\n\nFitur:\n• 974 modul fraktal produksi\n• Zoom dalam dan kontrol pan\n• 60+ skema warna dengan smooth coloring, orbit traps, estimasi jarak, relief normal-map, dan lainnya\n• Viewer ganda Mandelbrot / Julia\n• Mode auto-explore\n• Randomizer untuk tampilan baru secara instan\n• Looper untuk gerakan parameter animasi\n• Generasi Fractal Music dari pemindaian visual\n• Alat untuk menerapkan atau menyimpan wallpaper\n• Eksperimen overlay kamera yang tetap di perangkat\n• Alat ekspor dan berbagi\n• Aksesibilitas dengan kontras tinggi, pengurangan gerakan, label, dan target sentuh yang dapat diatur\n\nPrivat sejak awal: tanpa iklan, tanpa pelacakan, tanpa akun wajib, dan tanpa pengumpulan data."
    }
  }
}
